ftpsync/__init__.py
ftpsync/cli_common.py
ftpsync/ftp_target.py
ftpsync/metadata.py
ftpsync/pyftpsync.py
ftpsync/resources.py
ftpsync/run_command.py
ftpsync/scan_command.py
ftpsync/sftp_target.py
ftpsync/synchronizers.py
ftpsync/targets.py
ftpsync/tree_command.py
ftpsync/util.py
pyftpsync-4.1.0.data/data/CHANGELOG.md
pyftpsync-4.1.0.dist-info/LICENSE.txt
pyftpsync-4.1.0.dist-info/METADATA
pyftpsync-4.1.0.dist-info/WHEEL
pyftpsync-4.1.0.dist-info/entry_points.txt
pyftpsync-4.1.0.dist-info/top_level.txt
pyftpsync-4.1.0.dist-info/RECORD
