Metadata-Version: 2.1
Name: pyftpsync
Version: 4.1.0
Summary: Synchronize directories using FTP(S), SFTP, or file system access
Home-page: https://github.com/mar10/pyftpsync
Author: Martin Wendt
Author-email: pyftpsync@wwwendt.de
Maintainer: Martin Wendt
Maintainer-email: pyftpsync@wwwendt.de
License: MIT
Project-URL: Bug Tracker, https://github.com/mar10/pyftpsync/issues
Project-URL: Source Code, https://github.com/mar10/pyftpsync
Project-URL: Documentation, https://pyftpsync.readthedocs.io
Project-URL: Download, https://github.com/mar10/pyftpsync/releases/latest
Keywords: python,ftp,ftps,sftp,synchronize,tls,tool
Classifier: Development Status :: 4 - Beta
Classifier: Environment :: Console
Classifier: Intended Audience :: Developers
Classifier: Intended Audience :: Information Technology
Classifier: Intended Audience :: System Administrators
Classifier: License :: OSI Approved :: MIT License
Classifier: Operating System :: OS Independent
Classifier: Programming Language :: Python
Classifier: Programming Language :: Python :: 3
Classifier: Programming Language :: Python :: 3 :: Only
Classifier: Programming Language :: Python :: 3.8
Classifier: Programming Language :: Python :: 3.9
Classifier: Programming Language :: Python :: 3.10
Classifier: Programming Language :: Python :: 3.11
Classifier: Programming Language :: Python :: 3.12
Classifier: Topic :: Internet :: File Transfer Protocol (FTP)
Classifier: Topic :: Software Development :: Libraries :: Python Modules
Classifier: Topic :: Utilities
License-File: LICENSE.txt
Requires-Dist: colorama
Requires-Dist: keyring
Requires-Dist: pysftp
Requires-Dist: PyYAML
